vt_calc-0.0.4.dist-info/licenses/LICENSE
vt_calculator/__init__.py
vt_calculator/api.py
vt_calculator/reporter.py
vt_calculator/utils.py
vt_calculator/analysts/__init__.py
vt_calculator/analysts/analyst.py
vt_calculator/analysts/tools.py
vt_calculator/cli/__init__.py
vt_calculator/cli/handlers.py
vt_calculator/cli/main.py
vt_calculator/cli/parser.py
vt_calculator/video/__init__.py
vt_calculator/video/backends.py
vt_calculator/video/video.py
vt_calc-0.0.4.dist-info/METADATA
vt_calc-0.0.4.dist-info/WHEEL
vt_calc-0.0.4.dist-info/entry_points.txt
vt_calc-0.0.4.dist-info/top_level.txt
vt_calc-0.0.4.dist-info/RECORD
