Metadata-Version: 2.4
Name: vt-calc
Version: 0.0.4
Summary: Calculate the number of tokens used for images in VLMs
Home-page: https://github.com/thisisiron/vision-token-calculator
Author: Vision Token Calculator
Keywords: vision,tokens,language model,multimodal,ai,vlm,vision language model,vision language model token calculator
Classifier: Programming Language :: Python :: 3
Classifier: License :: OSI Approved :: MIT License
Classifier: Topic :: Scientific/Engineering :: Artificial Intelligence
Requires-Python: >=3.8
License-File: LICENSE
Requires-Dist: torch>=2.0.0
Requires-Dist: transformers<5.0.0,>=4.30.0
Requires-Dist: Pillow>=9.0.0
Requires-Dist: numpy>=1.21.0
Requires-Dist: requests>=2.25.0
Requires-Dist: av>=10.0.0
Requires-Dist: fastapi>=0.104.0
Requires-Dist: uvicorn[standard]>=0.24.0
Requires-Dist: jinja2>=3.1.0
Requires-Dist: python-multipart>=0.0.6
Requires-Dist: rich
Provides-Extra: video-advanced
Requires-Dist: decord>=0.6.0; extra == "video-advanced"
Requires-Dist: torchcodec>=0.1.0; extra == "video-advanced"
Provides-Extra: test
Requires-Dist: pytest>=7.0.0; extra == "test"
Requires-Dist: qwen-vl-utils>=0.0.8; extra == "test"
Requires-Dist: opencv-python>=4.5.0; extra == "test"
Provides-Extra: quality
Requires-Dist: ruff; extra == "quality"
Dynamic: author
Dynamic: classifier
Dynamic: description
Dynamic: description-content-type
Dynamic: home-page
Dynamic: keywords
Dynamic: license-file
Dynamic: provides-extra
Dynamic: requires-dist
Dynamic: requires-python
Dynamic: summary
